mycalc/calculator.py
yichaeyoung-1.0.1.dist-info/METADATA
yichaeyoung-1.0.1.dist-info/WHEEL
yichaeyoung-1.0.1.dist-info/top_level.txt
yichaeyoung-1.0.1.dist-info/RECORD
