Metadata-Version: 2.1
Name: yichaeyoung
Version: 1.0.1
Summary: coddyddld
Home-page: https://github.com/yichaeyoung/C-programming
Download-URL: https://github.com/yichaeyoung/C-programming/v.1.1.zip
Author: yichaeyoung
Author-email: 2243487@donga.ac.kr
License: UNKNOWN
Platform: UNKNOWN
Classifier: Programming Language :: Python :: 3
Classifier: Operating System :: OS Independent
